myFunction/__init__.py
myFunction/sentiment.py
myFunction-0.0.1.dist-info/METADATA
myFunction-0.0.1.dist-info/WHEEL
myFunction-0.0.1.dist-info/top_level.txt
myFunction-0.0.1.dist-info/RECORD
